maxxn
