Metadata-Version: 1.0
Name: maxxn
Version: 1.1.0
Summary: simple crawler
Home-page: UNKNOWN
Author: seraph0017
Author-email: seraph0017@hotmail.com
License: UNKNOWN
Keywords: simple crawler
Platform: any
